itereddit/__init__.py
itereddit/client.py
itereddit-1.0.1.dist-info/LICENSE
itereddit-1.0.1.dist-info/METADATA
itereddit-1.0.1.dist-info/WHEEL
itereddit-1.0.1.dist-info/top_level.txt
itereddit-1.0.1.dist-info/RECORD
