Metadata-Version: 2.1
Name: itereddit
Version: 1.0.1
Summary: Iterate posts from subreddit asynchronously
Home-page: https://github.com/WhiteApfel/itereddit
Author: WhiteApfel
Author-email: white@pfel.ru
License: Mozilla Public License 2.0
Project-URL: Donate, https://pfel.cc/donate
Project-URL: Source, https://github.com/WhiteApfel/itereddit
Project-URL: Telegram, https://t.me/apfel
Keywords: reddit wrapper
Platform: UNKNOWN
License-File: LICENSE
Requires-Dist: httpx (~=0.20.0)
Requires-Dist: pydantic (~=1.8.2)
